{
  "name": "electronic-arts",
  "data": [
    {
      "ID": "42",
      "Title": "Trapping Rain Water",
      "Acceptance": 48,
      "Difficulty": "Hard",
      "Frequency": "0.014929065877821017",
      "Link": " https://leetcode.com/problems/trapping-rain-water"
    },
    {
      "ID": "49",
      "Title": "Group Anagrams",
      "Acceptance": 56,
      "Difficulty": "Medium",
      "Frequency": "0.012769126803161552",
      "Link": " https://leetcode.com/problems/group-anagrams"
    },
    {
      "ID": "200",
      "Title": "Number of Islands",
      "Acceptance": 46,
      "Difficulty": "Medium",
      "Frequency": "0.00914807694576823",
      "Link": " https://leetcode.com/problems/number-of-islands"
    },
    {
      "ID": "206",
      "Title": "Reverse Linked List",
      "Acceptance": 62,
      "Difficulty": "Easy",
      "Frequency": "0.005257021452801617",
      "Link": " https://leetcode.com/problems/reverse-linked-list"
    },
    {
      "ID": "977",
      "Title": "Squares of a Sorted Array",
      "Acceptance": 72,
      "Difficulty": "Easy",
      "Frequency": "0.003891055492966611",
      "Link": " https://leetcode.com/problems/squares-of-a-sorted-array"
    }
  ]
}
