[
    {
        "ID": "244",
        "Title": "Shortest Word Distance II",
        "Acceptance": "52.3%",
        "Difficulty": "Medium",
        "Frequency": "6.080030276326555",
        "Leetcode Question Link": " https://leetcode.com/problems/shortest-word-distance-ii"
    },
    {
        "ID": "364",
        "Title": "Nested List Weight Sum II",
        "Acceptance": "62.8%",
        "Difficulty": "Medium",
        "Frequency": "5.858903208882962",
        "Leetcode Question Link": " https://leetcode.com/problems/nested-list-weight-sum-ii"
    },
    {
        "ID": "170",
        "Title": "Two Sum III - Data structure design",
        "Acceptance": "33.5%",
        "Difficulty": "Easy",
        "Frequency": "5.339976985176443",
        "Leetcode Question Link": " https://leetcode.com/problems/two-sum-iii-data-structure-design"
    },
    {
        "ID": "339",
        "Title": "Nested List Weight Sum",
        "Acceptance": "74.0%",
        "Difficulty": "Easy",
        "Frequency": "4.821050761469923",
        "Leetcode Question Link": " https://leetcode.com/problems/nested-list-weight-sum"
    },
    {
        "ID": "272",
        "Title": "Closest Binary Search Tree Value II",
        "Acceptance": "50.5%",
        "Difficulty": "Hard",
        "Frequency": "4.69866052907543",
        "Leetcode Question Link": " https://leetcode.com/problems/closest-binary-search-tree-value-ii"
    },
    {
        "ID": "156",
        "Title": "Binary Tree Upside Down",
        "Acceptance": "55.0%",
        "Difficulty": "Medium",
        "Frequency": "4.677621857655682",
        "Leetcode Question Link": " https://leetcode.com/problems/binary-tree-upside-down"
    },
    {
        "ID": "716",
        "Title": "Max Stack",
        "Acceptance": "42.6%",
        "Difficulty": "Easy",
        "Frequency": "4.158695633949162",
        "Leetcode Question Link": " https://leetcode.com/problems/max-stack"
    },
    {
        "ID": "254",
        "Title": "Factor Combinations",
        "Acceptance": "46.7%",
        "Difficulty": "Medium",
        "Frequency": "4.042679900269238",
        "Leetcode Question Link": " https://leetcode.com/problems/factor-combinations"
    },
    {
        "ID": "243",
        "Title": "Shortest Word Distance",
        "Acceptance": "61.0%",
        "Difficulty": "Easy",
        "Frequency": "4.033402295442248",
        "Leetcode Question Link": " https://leetcode.com/problems/shortest-word-distance"
    },
    {
        "ID": "366",
        "Title": "Find Leaves of Binary Tree",
        "Acceptance": "70.6%",
        "Difficulty": "Medium",
        "Frequency": "3.8874042537463542",
        "Leetcode Question Link": " https://leetcode.com/problems/find-leaves-of-binary-tree"
    },
    {
        "ID": "256",
        "Title": "Paint House",
        "Acceptance": "52.1%",
        "Difficulty": "Easy",
        "Frequency": "3.830168081045509",
        "Leetcode Question Link": " https://leetcode.com/problems/paint-house"
    },
    {
        "ID": "265",
        "Title": "Paint House II",
        "Acceptance": "44.6%",
        "Difficulty": "Hard",
        "Frequency": "3.643918157363893",
        "Leetcode Question Link": " https://leetcode.com/problems/paint-house-ii"
    },
    {
        "ID": "149",
        "Title": "Max Points on a Line",
        "Acceptance": "16.9%",
        "Difficulty": "Hard",
        "Frequency": "3.593946561618369",
        "Leetcode Question Link": " https://leetcode.com/problems/max-points-on-a-line"
    },
    {
        "ID": "65",
        "Title": "Valid Number",
        "Acceptance": "15.3%",
        "Difficulty": "Hard",
        "Frequency": "3.4859422228274832",
        "Leetcode Question Link": " https://leetcode.com/problems/valid-number"
    },
    {
        "ID": "605",
        "Title": "Can Place Flowers",
        "Acceptance": "31.6%",
        "Difficulty": "Easy",
        "Frequency": "3.393038148985481",
        "Leetcode Question Link": " https://leetcode.com/problems/can-place-flowers"
    },
    {
        "ID": "380",
        "Title": "Insert Delete GetRandom O(1)",
        "Acceptance": "47.5%",
        "Difficulty": "Medium",
        "Frequency": "3.226132922031484",
        "Leetcode Question Link": " https://leetcode.com/problems/insert-delete-getrandom-o1"
    },
    {
        "ID": "432",
        "Title": "All O`one Data Structure",
        "Acceptance": "32.4%",
        "Difficulty": "Hard",
        "Frequency": "3.182278405836062",
        "Leetcode Question Link": " https://leetcode.com/problems/all-oone-data-structure"
    },
    {
        "ID": "68",
        "Title": "Text Justification",
        "Acceptance": "27.7%",
        "Difficulty": "Hard",
        "Frequency": "3.1683420251214285",
        "Leetcode Question Link": " https://leetcode.com/problems/text-justification"
    },
    {
        "ID": "341",
        "Title": "Flatten Nested List Iterator",
        "Acceptance": "52.9%",
        "Difficulty": "Medium",
        "Frequency": "2.8560409644057407",
        "Leetcode Question Link": " https://leetcode.com/problems/flatten-nested-list-iterator"
    },
    {
        "ID": "150",
        "Title": "Evaluate Reverse Polish Notation",
        "Acceptance": "36.3%",
        "Difficulty": "Medium",
        "Frequency": "2.7457641678571494",
        "Leetcode Question Link": " https://leetcode.com/problems/evaluate-reverse-polish-notation"
    },
    {
        "ID": "205",
        "Title": "Isomorphic Strings",
        "Acceptance": "39.8%",
        "Difficulty": "Easy",
        "Frequency": "2.6687791722177048",
        "Leetcode Question Link": " https://leetcode.com/problems/isomorphic-strings"
    },
    {
        "ID": "245",
        "Title": "Shortest Word Distance III",
        "Acceptance": "55.3%",
        "Difficulty": "Medium",
        "Frequency": "2.4804776643766675",
        "Leetcode Question Link": " https://leetcode.com/problems/shortest-word-distance-iii"
    },
    {
        "ID": "297",
        "Title": "Serialize and Deserialize Binary Tree",
        "Acceptance": "47.5%",
        "Difficulty": "Hard",
        "Frequency": "2.4208730516603993",
        "Leetcode Question Link": " https://leetcode.com/problems/serialize-and-deserialize-binary-tree"
    },
    {
        "ID": "261",
        "Title": "Graph Valid Tree",
        "Acceptance": "42.2%",
        "Difficulty": "Medium",
        "Frequency": "2.361420232509446",
        "Leetcode Question Link": " https://leetcode.com/problems/graph-valid-tree"
    },
    {
        "ID": "611",
        "Title": "Valid Triangle Number",
        "Acceptance": "48.4%",
        "Difficulty": "Medium",
        "Frequency": "2.3166166237983035",
        "Leetcode Question Link": " https://leetcode.com/problems/valid-triangle-number"
    },
    {
        "ID": "730",
        "Title": "Count Different Palindromic Subsequences",
        "Acceptance": "41.8%",
        "Difficulty": "Hard",
        "Frequency": "2.3008291662917806",
        "Leetcode Question Link": " https://leetcode.com/problems/count-different-palindromic-subsequences"
    },
    {
        "ID": "53",
        "Title": "Maximum Subarray",
        "Acceptance": "46.5%",
        "Difficulty": "Easy",
        "Frequency": "2.234231225147922",
        "Leetcode Question Link": " https://leetcode.com/problems/maximum-subarray"
    },
    {
        "ID": "187",
        "Title": "Repeated DNA Sequences",
        "Acceptance": "38.9%",
        "Difficulty": "Medium",
        "Frequency": "2.1034320303164904",
        "Leetcode Question Link": " https://leetcode.com/problems/repeated-dna-sequences"
    },
    {
        "ID": "698",
        "Title": "Partition to K Equal Sum Subsets",
        "Acceptance": "45.0%",
        "Difficulty": "Medium",
        "Frequency": "2.0188752204026974",
        "Leetcode Question Link": " https://leetcode.com/problems/partition-to-k-equal-sum-subsets"
    },
    {
        "ID": "152",
        "Title": "Maximum Product Subarray",
        "Acceptance": "31.7%",
        "Difficulty": "Medium",
        "Frequency": "2.012330220619989",
        "Leetcode Question Link": " https://leetcode.com/problems/maximum-product-subarray"
    },
    {
        "ID": "72",
        "Title": "Edit Distance",
        "Acceptance": "44.8%",
        "Difficulty": "Hard",
        "Frequency": "1.77034719073246",
        "Leetcode Question Link": " https://leetcode.com/problems/edit-distance"
    },
    {
        "ID": "200",
        "Title": "Number of Islands",
        "Acceptance": "46.8%",
        "Difficulty": "Medium",
        "Frequency": "1.7486397840620904",
        "Leetcode Question Link": " https://leetcode.com/problems/number-of-islands"
    },
    {
        "ID": "277",
        "Title": "Find the Celebrity",
        "Acceptance": "41.8%",
        "Difficulty": "Medium",
        "Frequency": "1.6753413644780486",
        "Leetcode Question Link": " https://leetcode.com/problems/find-the-celebrity"
    },
    {
        "ID": "56",
        "Title": "Merge Intervals",
        "Acceptance": "39.3%",
        "Difficulty": "Medium",
        "Frequency": "1.660437199438034",
        "Leetcode Question Link": " https://leetcode.com/problems/merge-intervals"
    },
    {
        "ID": "516",
        "Title": "Longest Palindromic Subsequence",
        "Acceptance": "53.2%",
        "Difficulty": "Medium",
        "Frequency": "1.6283626316034112",
        "Leetcode Question Link": " https://leetcode.com/problems/longest-palindromic-subsequence"
    },
    {
        "ID": "671",
        "Title": "Second Minimum Node In a Binary Tree",
        "Acceptance": "42.7%",
        "Difficulty": "Easy",
        "Frequency": "1.6037158670068572",
        "Leetcode Question Link": " https://leetcode.com/problems/second-minimum-node-in-a-binary-tree"
    },
    {
        "ID": "76",
        "Title": "Minimum Window Substring",
        "Acceptance": "34.6%",
        "Difficulty": "Hard",
        "Frequency": "1.5906343171159958",
        "Leetcode Question Link": " https://leetcode.com/problems/minimum-window-substring"
    },
    {
        "ID": "464",
        "Title": "Can I Win",
        "Acceptance": "28.8%",
        "Difficulty": "Medium",
        "Frequency": "1.506328285095676",
        "Leetcode Question Link": " https://leetcode.com/problems/can-i-win"
    },
    {
        "ID": "236",
        "Title": "Lowest Common Ancestor of a Binary Tree",
        "Acceptance": "45.7%",
        "Difficulty": "Medium",
        "Frequency": "1.4917287074839412",
        "Leetcode Question Link": " https://leetcode.com/problems/lowest-common-ancestor-of-a-binary-tree"
    },
    {
        "ID": "12",
        "Title": "Integer to Roman",
        "Acceptance": "55.1%",
        "Difficulty": "Medium",
        "Frequency": "1.4878558960006285",
        "Leetcode Question Link": " https://leetcode.com/problems/integer-to-roman"
    },
    {
        "ID": "373",
        "Title": "Find K Pairs with Smallest Sums",
        "Acceptance": "36.7%",
        "Difficulty": "Medium",
        "Frequency": "1.4398887318809226",
        "Leetcode Question Link": " https://leetcode.com/problems/find-k-pairs-with-smallest-sums"
    },
    {
        "ID": "235",
        "Title": "Lowest Common Ancestor of a Binary Search Tree",
        "Acceptance": "49.9%",
        "Difficulty": "Easy",
        "Frequency": "1.4200618278990031",
        "Leetcode Question Link": " https://leetcode.com/problems/lowest-common-ancestor-of-a-binary-search-tree"
    },
    {
        "ID": "102",
        "Title": "Binary Tree Level Order Traversal",
        "Acceptance": "54.6%",
        "Difficulty": "Medium",
        "Frequency": "1.4026563080569336",
        "Leetcode Question Link": " https://leetcode.com/problems/binary-tree-level-order-traversal"
    },
    {
        "ID": "381",
        "Title": "Insert Delete GetRandom O(1) - Duplicates allowed",
        "Acceptance": "34.1%",
        "Difficulty": "Hard",
        "Frequency": "1.4015377574600891",
        "Leetcode Question Link": " https://leetcode.com/problems/insert-delete-getrandom-o1-duplicates-allowed"
    },
    {
        "ID": "1",
        "Title": "Two Sum",
        "Acceptance": "45.6%",
        "Difficulty": "Easy",
        "Frequency": "1.3998908606433091",
        "Leetcode Question Link": " https://leetcode.com/problems/two-sum"
    },
    {
        "ID": "50",
        "Title": "Pow(x;n)",
        "Acceptance": "30.3%",
        "Difficulty": "Medium",
        "Frequency": "1.295878904893276",
        "Leetcode Question Link": " https://leetcode.com/problems/powx-n"
    },
    {
        "ID": "33",
        "Title": "Search in Rotated Sorted Array",
        "Acceptance": "34.5%",
        "Difficulty": "Medium",
        "Frequency": "1.2373938135133047",
        "Leetcode Question Link": " https://leetcode.com/problems/search-in-rotated-sorted-array"
    },
    {
        "ID": "20",
        "Title": "Valid Parentheses",
        "Acceptance": "39.0%",
        "Difficulty": "Easy",
        "Frequency": "1.2333689145339155",
        "Leetcode Question Link": " https://leetcode.com/problems/valid-parentheses"
    },
    {
        "ID": "273",
        "Title": "Integer to English Words",
        "Acceptance": "27.1%",
        "Difficulty": "Hard",
        "Frequency": "1.2185425385498858",
        "Leetcode Question Link": " https://leetcode.com/problems/integer-to-english-words"
    },
    {
        "ID": "34",
        "Title": "Find First and Last Position of Element in Sorted Array",
        "Acceptance": "36.2%",
        "Difficulty": "Medium",
        "Frequency": "1.2091842728345334",
        "Leetcode Question Link": " https://leetcode.com/problems/find-first-and-last-position-of-element-in-sorted-array"
    },
    {
        "ID": "127",
        "Title": "Word Ladder",
        "Acceptance": "29.6%",
        "Difficulty": "Medium",
        "Frequency": "1.1879531176262481",
        "Leetcode Question Link": " https://leetcode.com/problems/word-ladder"
    },
    {
        "ID": "57",
        "Title": "Insert Interval",
        "Acceptance": "33.5%",
        "Difficulty": "Hard",
        "Frequency": "1.1730267742341929",
        "Leetcode Question Link": " https://leetcode.com/problems/insert-interval"
    },
    {
        "ID": "636",
        "Title": "Exclusive Time of Functions",
        "Acceptance": "51.9%",
        "Difficulty": "Medium",
        "Frequency": "1.1392005862073036",
        "Leetcode Question Link": " https://leetcode.com/problems/exclusive-time-of-functions"
    },
    {
        "ID": "384",
        "Title": "Shuffle an Array",
        "Acceptance": "52.8%",
        "Difficulty": "Medium",
        "Frequency": "0.991100943542345",
        "Leetcode Question Link": " https://leetcode.com/problems/shuffle-an-array"
    },
    {
        "ID": "1117",
        "Title": "Building H2O",
        "Acceptance": "52.6%",
        "Difficulty": "Medium",
        "Frequency": "0.9829600869737358",
        "Leetcode Question Link": " https://leetcode.com/problems/building-h2o"
    },
    {
        "ID": "69",
        "Title": "Sqrt(x)",
        "Acceptance": "33.9%",
        "Difficulty": "Easy",
        "Frequency": "0.9425416082510271",
        "Leetcode Question Link": " https://leetcode.com/problems/sqrtx"
    },
    {
        "ID": "146",
        "Title": "LRU Cache",
        "Acceptance": "33.2%",
        "Difficulty": "Medium",
        "Frequency": "0.9138670478439253",
        "Leetcode Question Link": " https://leetcode.com/problems/lru-cache"
    },
    {
        "ID": "46",
        "Title": "Permutations",
        "Acceptance": "63.5%",
        "Difficulty": "Medium",
        "Frequency": "0.8944850434890723",
        "Leetcode Question Link": " https://leetcode.com/problems/permutations"
    },
    {
        "ID": "655",
        "Title": "Print Binary Tree",
        "Acceptance": "55.0%",
        "Difficulty": "Medium",
        "Frequency": "0.8942200477548448",
        "Leetcode Question Link": " https://leetcode.com/problems/print-binary-tree"
    },
    {
        "ID": "13",
        "Title": "Roman to Integer",
        "Acceptance": "55.7%",
        "Difficulty": "Easy",
        "Frequency": "0.8933962612312258",
        "Leetcode Question Link": " https://leetcode.com/problems/roman-to-integer"
    },
    {
        "ID": "744",
        "Title": "Find Smallest Letter Greater Than Target",
        "Acceptance": "45.4%",
        "Difficulty": "Easy",
        "Frequency": "0.8539612853364241",
        "Leetcode Question Link": " https://leetcode.com/problems/find-smallest-letter-greater-than-target"
    },
    {
        "ID": "215",
        "Title": "Kth Largest Element in an Array",
        "Acceptance": "55.4%",
        "Difficulty": "Medium",
        "Frequency": "0.7561265689929935",
        "Leetcode Question Link": " https://leetcode.com/problems/kth-largest-element-in-an-array"
    },
    {
        "ID": "449",
        "Title": "Serialize and Deserialize BST",
        "Acceptance": "52.0%",
        "Difficulty": "Medium",
        "Frequency": "0.7481106198504164",
        "Leetcode Question Link": " https://leetcode.com/problems/serialize-and-deserialize-bst"
    },
    {
        "ID": "715",
        "Title": "Range Module",
        "Acceptance": "38.5%",
        "Difficulty": "Hard",
        "Frequency": "0.7472144018302211",
        "Leetcode Question Link": " https://leetcode.com/problems/range-module"
    },
    {
        "ID": "296",
        "Title": "Best Meeting Point",
        "Acceptance": "57.5%",
        "Difficulty": "Hard",
        "Frequency": "0.7267024804081622",
        "Leetcode Question Link": " https://leetcode.com/problems/best-meeting-point"
    },
    {
        "ID": "1188",
        "Title": "Design Bounded Blocking Queue",
        "Acceptance": "70.5%",
        "Difficulty": "Medium",
        "Frequency": "0.7176264446447249",
        "Leetcode Question Link": " https://leetcode.com/problems/design-bounded-blocking-queue"
    },
    {
        "ID": "460",
        "Title": "LFU Cache",
        "Acceptance": "34.2%",
        "Difficulty": "Hard",
        "Frequency": "0.668474221864485",
        "Leetcode Question Link": " https://leetcode.com/problems/lfu-cache"
    },
    {
        "ID": "126",
        "Title": "Word Ladder II",
        "Acceptance": "22.1%",
        "Difficulty": "Hard",
        "Frequency": "0.6364159003926323",
        "Leetcode Question Link": " https://leetcode.com/problems/word-ladder-ii"
    },
    {
        "ID": "160",
        "Title": "Intersection of Two Linked Lists",
        "Acceptance": "40.6%",
        "Difficulty": "Easy",
        "Frequency": "0.6045153022014824",
        "Leetcode Question Link": " https://leetcode.com/problems/intersection-of-two-linked-lists"
    },
    {
        "ID": "101",
        "Title": "Symmetric Tree",
        "Acceptance": "46.8%",
        "Difficulty": "Easy",
        "Frequency": "0.5986256023076202",
        "Leetcode Question Link": " https://leetcode.com/problems/symmetric-tree"
    },
    {
        "ID": "879",
        "Title": "Profitable Schemes",
        "Acceptance": "39.8%",
        "Difficulty": "Hard",
        "Frequency": "0.5560675878793254",
        "Leetcode Question Link": " https://leetcode.com/problems/profitable-schemes"
    },
    {
        "ID": "47",
        "Title": "Permutations II",
        "Acceptance": "46.4%",
        "Difficulty": "Medium",
        "Frequency": "0.5319853456599372",
        "Leetcode Question Link": " https://leetcode.com/problems/permutations-ii"
    },
    {
        "ID": "104",
        "Title": "Maximum Depth of Binary Tree",
        "Acceptance": "66.0%",
        "Difficulty": "Easy",
        "Frequency": "0.513251489692768",
        "Leetcode Question Link": " https://leetcode.com/problems/maximum-depth-of-binary-tree"
    },
    {
        "ID": "706",
        "Title": "Design HashMap",
        "Acceptance": "61.3%",
        "Difficulty": "Easy",
        "Frequency": "0.49262383645737706",
        "Leetcode Question Link": " https://leetcode.com/problems/design-hashmap"
    },
    {
        "ID": "412",
        "Title": "Fizz Buzz",
        "Acceptance": "62.3%",
        "Difficulty": "Easy",
        "Frequency": "0.4590212125771265",
        "Leetcode Question Link": " https://leetcode.com/problems/fizz-buzz"
    },
    {
        "ID": "311",
        "Title": "Sparse Matrix Multiplication",
        "Acceptance": "61.9%",
        "Difficulty": "Medium",
        "Frequency": "0.4503238876572249",
        "Leetcode Question Link": " https://leetcode.com/problems/sparse-matrix-multiplication"
    },
    {
        "ID": "8",
        "Title": "String to Integer (atoi)",
        "Acceptance": "15.4%",
        "Difficulty": "Medium",
        "Frequency": "0.407141925712164",
        "Leetcode Question Link": " https://leetcode.com/problems/string-to-integer-atoi"
    },
    {
        "ID": "739",
        "Title": "Daily Temperatures",
        "Acceptance": "63.3%",
        "Difficulty": "Medium",
        "Frequency": "0.40150804127350803",
        "Leetcode Question Link": " https://leetcode.com/problems/daily-temperatures"
    },
    {
        "ID": "323",
        "Title": "Number of Connected Components in an Undirected Graph",
        "Acceptance": "56.0%",
        "Difficulty": "Medium",
        "Frequency": "0.32984288327605893",
        "Leetcode Question Link": " https://leetcode.com/problems/number-of-connected-components-in-an-undirected-graph"
    },
    {
        "ID": "367",
        "Title": "Valid Perfect Square",
        "Acceptance": "41.7%",
        "Difficulty": "Easy",
        "Frequency": "0.3203744341373232",
        "Leetcode Question Link": " https://leetcode.com/problems/valid-perfect-square"
    },
    {
        "ID": "61",
        "Title": "Rotate List",
        "Acceptance": "30.0%",
        "Difficulty": "Medium",
        "Frequency": "0.3068243673566749",
        "Leetcode Question Link": " https://leetcode.com/problems/rotate-list"
    },
    {
        "ID": "349",
        "Title": "Intersection of Two Arrays",
        "Acceptance": "62.5%",
        "Difficulty": "Easy",
        "Frequency": "0.3049506996831345",
        "Leetcode Question Link": " https://leetcode.com/problems/intersection-of-two-arrays"
    },
    {
        "ID": "23",
        "Title": "Merge k Sorted Lists",
        "Acceptance": "40.2%",
        "Difficulty": "Hard",
        "Frequency": "0.28430175890527876",
        "Leetcode Question Link": " https://leetcode.com/problems/merge-k-sorted-lists"
    },
    {
        "ID": "547",
        "Title": "Friend Circles",
        "Acceptance": "58.6%",
        "Difficulty": "Medium",
        "Frequency": "0.2681916080548848",
        "Leetcode Question Link": " https://leetcode.com/problems/friend-circles"
    },
    {
        "ID": "450",
        "Title": "Delete Node in a BST",
        "Acceptance": "43.1%",
        "Difficulty": "Medium",
        "Frequency": "0.2618604317292985",
        "Leetcode Question Link": " https://leetcode.com/problems/delete-node-in-a-bst"
    },
    {
        "ID": "470",
        "Title": "Implement Rand10() Using Rand7()",
        "Acceptance": "46.3%",
        "Difficulty": "Medium",
        "Frequency": "0.2553466918088445",
        "Leetcode Question Link": " https://leetcode.com/problems/implement-rand10-using-rand7"
    },
    {
        "ID": "173",
        "Title": "Binary Search Tree Iterator",
        "Acceptance": "56.6%",
        "Difficulty": "Medium",
        "Frequency": "0.22943234572951865",
        "Leetcode Question Link": " https://leetcode.com/problems/binary-search-tree-iterator"
    },
    {
        "ID": "796",
        "Title": "Rotate String",
        "Acceptance": "49.6%",
        "Difficulty": "Easy",
        "Frequency": "0.22026466797690847",
        "Leetcode Question Link": " https://leetcode.com/problems/rotate-string"
    },
    {
        "ID": "528",
        "Title": "Random Pick with Weight",
        "Acceptance": "43.9%",
        "Difficulty": "Medium",
        "Frequency": "0.21436399542669993",
        "Leetcode Question Link": " https://leetcode.com/problems/random-pick-with-weight"
    },
    {
        "ID": "322",
        "Title": "Coin Change",
        "Acceptance": "35.5%",
        "Difficulty": "Medium",
        "Frequency": "0.20468224088850068",
        "Leetcode Question Link": " https://leetcode.com/problems/coin-change"
    },
    {
        "ID": "40",
        "Title": "Combination Sum II",
        "Acceptance": "48.2%",
        "Difficulty": "Medium",
        "Frequency": "0.1780616138489939",
        "Leetcode Question Link": " https://leetcode.com/problems/combination-sum-ii"
    },
    {
        "ID": "88",
        "Title": "Merge Sorted Array",
        "Acceptance": "39.4%",
        "Difficulty": "Easy",
        "Frequency": "0.17642540243837188",
        "Leetcode Question Link": " https://leetcode.com/problems/merge-sorted-array"
    },
    {
        "ID": "721",
        "Title": "Accounts Merge",
        "Acceptance": "48.8%",
        "Difficulty": "Medium",
        "Frequency": "0.15836350116973763",
        "Leetcode Question Link": " https://leetcode.com/problems/accounts-merge"
    },
    {
        "ID": "155",
        "Title": "Min Stack",
        "Acceptance": "44.5%",
        "Difficulty": "Easy",
        "Frequency": "0.15817175770099312",
        "Leetcode Question Link": " https://leetcode.com/problems/min-stack"
    },
    {
        "ID": "1148",
        "Title": "Article Views I",
        "Acceptance": "75.8%",
        "Difficulty": "Easy",
        "Frequency": "0.15441568579144338",
        "Leetcode Question Link": " https://leetcode.com/problems/article-views-i"
    },
    {
        "ID": "39",
        "Title": "Combination Sum",
        "Acceptance": "56.1%",
        "Difficulty": "Medium",
        "Frequency": "0.1339254107186325",
        "Leetcode Question Link": " https://leetcode.com/problems/combination-sum"
    },
    {
        "ID": "428",
        "Title": "Serialize and Deserialize N-ary Tree",
        "Acceptance": "59.4%",
        "Difficulty": "Hard",
        "Frequency": "0.13313574474596881",
        "Leetcode Question Link": " https://leetcode.com/problems/serialize-and-deserialize-n-ary-tree"
    },
    {
        "ID": "54",
        "Title": "Spiral Matrix",
        "Acceptance": "34.1%",
        "Difficulty": "Medium",
        "Frequency": "0.12572728493821236",
        "Leetcode Question Link": " https://leetcode.com/problems/spiral-matrix"
    },
    {
        "ID": "1042",
        "Title": "Flower Planting With No Adjacent",
        "Acceptance": "48.5%",
        "Difficulty": "Easy",
        "Frequency": "0.125457954276896",
        "Leetcode Question Link": " https://leetcode.com/problems/flower-planting-with-no-adjacent"
    },
    {
        "ID": "21",
        "Title": "Merge Two Sorted Lists",
        "Acceptance": "53.5%",
        "Difficulty": "Easy",
        "Frequency": "0.11955628018646022",
        "Leetcode Question Link": " https://leetcode.com/problems/merge-two-sorted-lists"
    },
    {
        "ID": "75",
        "Title": "Sort Colors",
        "Acceptance": "47.3%",
        "Difficulty": "Medium",
        "Frequency": "0.11789425180508288",
        "Leetcode Question Link": " https://leetcode.com/problems/sort-colors"
    },
    {
        "ID": "103",
        "Title": "Binary Tree Zigzag Level Order Traversal",
        "Acceptance": "48.3%",
        "Difficulty": "Medium",
        "Frequency": "0.11648551004070631",
        "Leetcode Question Link": " https://leetcode.com/problems/binary-tree-zigzag-level-order-traversal"
    },
    {
        "ID": "451",
        "Title": "Sort Characters By Frequency",
        "Acceptance": "63.0%",
        "Difficulty": "Medium",
        "Frequency": "0.11258362132121401",
        "Leetcode Question Link": " https://leetcode.com/problems/sort-characters-by-frequency"
    },
    {
        "ID": "973",
        "Title": "K Closest Points to Origin",
        "Acceptance": "63.8%",
        "Difficulty": "Medium",
        "Frequency": "0.11087510283099485",
        "Leetcode Question Link": " https://leetcode.com/problems/k-closest-points-to-origin"
    },
    {
        "ID": "198",
        "Title": "House Robber",
        "Acceptance": "42.0%",
        "Difficulty": "Easy",
        "Frequency": "0.10785152815546674",
        "Leetcode Question Link": " https://leetcode.com/problems/house-robber"
    },
    {
        "ID": "1028",
        "Title": "Recover a Tree From Preorder Traversal",
        "Acceptance": "69.9%",
        "Difficulty": "Hard",
        "Frequency": "0.10734155493596446",
        "Leetcode Question Link": " https://leetcode.com/problems/recover-a-tree-from-preorder-traversal"
    },
    {
        "ID": "238",
        "Title": "Product of Array Except Self",
        "Acceptance": "60.1%",
        "Difficulty": "Medium",
        "Frequency": "0.09390398065367858",
        "Leetcode Question Link": " https://leetcode.com/problems/product-of-array-except-self"
    },
    {
        "ID": "833",
        "Title": "Find And Replace in String",
        "Acceptance": "50.4%",
        "Difficulty": "Medium",
        "Frequency": "0.08751937801655657",
        "Leetcode Question Link": " https://leetcode.com/problems/find-and-replace-in-string"
    },
    {
        "ID": "100",
        "Title": "Same Tree",
        "Acceptance": "53.4%",
        "Difficulty": "Easy",
        "Frequency": "0.08633894223670877",
        "Leetcode Question Link": " https://leetcode.com/problems/same-tree"
    },
    {
        "ID": "350",
        "Title": "Intersection of Two Arrays II",
        "Acceptance": "51.4%",
        "Difficulty": "Easy",
        "Frequency": "0.08027374155116185",
        "Leetcode Question Link": " https://leetcode.com/problems/intersection-of-two-arrays-ii"
    },
    {
        "ID": "133",
        "Title": "Clone Graph",
        "Acceptance": "34.8%",
        "Difficulty": "Medium",
        "Frequency": "0.07095173597228444",
        "Leetcode Question Link": " https://leetcode.com/problems/clone-graph"
    },
    {
        "ID": "270",
        "Title": "Closest Binary Search Tree Value",
        "Acceptance": "48.5%",
        "Difficulty": "Easy",
        "Frequency": "0.06680279511160087",
        "Leetcode Question Link": " https://leetcode.com/problems/closest-binary-search-tree-value"
    },
    {
        "ID": "98",
        "Title": "Validate Binary Search Tree",
        "Acceptance": "27.8%",
        "Difficulty": "Medium",
        "Frequency": "0.057985181512132535",
        "Leetcode Question Link": " https://leetcode.com/problems/validate-binary-search-tree"
    },
    {
        "ID": "362",
        "Title": "Design Hit Counter",
        "Acceptance": "63.7%",
        "Difficulty": "Medium",
        "Frequency": "0.05622967649867821",
        "Leetcode Question Link": " https://leetcode.com/problems/design-hit-counter"
    },
    {
        "ID": "981",
        "Title": "Time Based Key-Value Store",
        "Acceptance": "53.1%",
        "Difficulty": "Medium",
        "Frequency": "0.049406315387071284",
        "Leetcode Question Link": " https://leetcode.com/problems/time-based-key-value-store"
    },
    {
        "ID": "121",
        "Title": "Best Time to Buy and Sell Stock",
        "Acceptance": "50.5%",
        "Difficulty": "Easy",
        "Frequency": "0.04215422741819192",
        "Leetcode Question Link": " https://leetcode.com/problems/best-time-to-buy-and-sell-stock"
    },
    {
        "ID": "647",
        "Title": "Palindromic Substrings",
        "Acceptance": "60.6%",
        "Difficulty": "Medium",
        "Frequency": "0.040968350772541844",
        "Leetcode Question Link": " https://leetcode.com/problems/palindromic-substrings"
    },
    {
        "ID": "141",
        "Title": "Linked List Cycle",
        "Acceptance": "41.1%",
        "Difficulty": "Easy",
        "Frequency": "0.031012908394529512",
        "Leetcode Question Link": " https://leetcode.com/problems/linked-list-cycle"
    },
    {
        "ID": "240",
        "Title": "Search a 2D Matrix II",
        "Acceptance": "43.2%",
        "Difficulty": "Medium",
        "Frequency": "0.02999287612403949",
        "Leetcode Question Link": " https://leetcode.com/problems/search-a-2d-matrix-ii"
    },
    {
        "ID": "692",
        "Title": "Top K Frequent Words",
        "Acceptance": "51.8%",
        "Difficulty": "Medium",
        "Frequency": "0.029730915184679466",
        "Leetcode Question Link": " https://leetcode.com/problems/top-k-frequent-words"
    },
    {
        "ID": "987",
        "Title": "Vertical Order Traversal of a Binary Tree",
        "Acceptance": "36.6%",
        "Difficulty": "Medium",
        "Frequency": "0.025915645579833068",
        "Leetcode Question Link": " https://leetcode.com/problems/vertical-order-traversal-of-a-binary-tree"
    },
    {
        "ID": "387",
        "Title": "First Unique Character in a String",
        "Acceptance": "53.4%",
        "Difficulty": "Easy",
        "Frequency": "0.02587600384690711",
        "Leetcode Question Link": " https://leetcode.com/problems/first-unique-character-in-a-string"
    },
    {
        "ID": "785",
        "Title": "Is Graph Bipartite?",
        "Acceptance": "47.5%",
        "Difficulty": "Medium",
        "Frequency": "0.02510592113107633",
        "Leetcode Question Link": " https://leetcode.com/problems/is-graph-bipartite"
    },
    {
        "ID": "70",
        "Title": "Climbing Stairs",
        "Acceptance": "47.8%",
        "Difficulty": "Easy",
        "Frequency": "0.023866591309041507",
        "Leetcode Question Link": " https://leetcode.com/problems/climbing-stairs"
    },
    {
        "ID": "113",
        "Title": "Path Sum II",
        "Acceptance": "46.7%",
        "Difficulty": "Medium",
        "Frequency": "0.021882711249507664",
        "Leetcode Question Link": " https://leetcode.com/problems/path-sum-ii"
    },
    {
        "ID": "359",
        "Title": "Logger Rate Limiter",
        "Acceptance": "70.8%",
        "Difficulty": "Easy",
        "Frequency": "0.021053409197832343",
        "Leetcode Question Link": " https://leetcode.com/problems/logger-rate-limiter"
    },
    {
        "ID": "207",
        "Title": "Course Schedule",
        "Acceptance": "43.1%",
        "Difficulty": "Medium",
        "Frequency": "0.019709926055136454",
        "Leetcode Question Link": " https://leetcode.com/problems/course-schedule"
    },
    {
        "ID": "347",
        "Title": "Top K Frequent Elements",
        "Acceptance": "61.2%",
        "Difficulty": "Medium",
        "Frequency": "0.018049036874660983",
        "Leetcode Question Link": " https://leetcode.com/problems/top-k-frequent-elements"
    },
    {
        "ID": "79",
        "Title": "Word Search",
        "Acceptance": "35.6%",
        "Difficulty": "Medium",
        "Frequency": "0.014883688014740005",
        "Leetcode Question Link": " https://leetcode.com/problems/word-search"
    },
    {
        "ID": "142",
        "Title": "Linked List Cycle II",
        "Acceptance": "37.3%",
        "Difficulty": "Medium",
        "Frequency": "0.014710955064667802",
        "Leetcode Question Link": " https://leetcode.com/problems/linked-list-cycle-ii"
    },
    {
        "ID": "560",
        "Title": "Subarray Sum Equals K",
        "Acceptance": "43.9%",
        "Difficulty": "Medium",
        "Frequency": "0.009603146783199741",
        "Leetcode Question Link": " https://leetcode.com/problems/subarray-sum-equals-k"
    },
    {
        "ID": "279",
        "Title": "Perfect Squares",
        "Acceptance": "47.4%",
        "Difficulty": "Medium",
        "Frequency": "0.009216655104924008",
        "Leetcode Question Link": " https://leetcode.com/problems/perfect-squares"
    },
    {
        "ID": "125",
        "Title": "Valid Palindrome",
        "Acceptance": "36.7%",
        "Difficulty": "Easy",
        "Frequency": "0.008933948641551634",
        "Leetcode Question Link": " https://leetcode.com/problems/valid-palindrome"
    },
    {
        "ID": "515",
        "Title": "Find Largest Value in Each Tree Row",
        "Acceptance": "61.1%",
        "Difficulty": "Medium",
        "Frequency": "0",
        "Leetcode Question Link": " https://leetcode.com/problems/find-largest-value-in-each-tree-row"
    },
    {
        "ID": "633",
        "Title": "Sum of Square Numbers",
        "Acceptance": "32.2%",
        "Difficulty": "Easy",
        "Frequency": "0",
        "Leetcode Question Link": " https://leetcode.com/problems/sum-of-square-numbers"
    },
    {
        "ID": "946",
        "Title": "Validate Stack Sequences",
        "Acceptance": "61.9%",
        "Difficulty": "Medium",
        "Frequency": "0",
        "Leetcode Question Link": " https://leetcode.com/problems/validate-stack-sequences"
    },
    {
        "ID": "1107",
        "Title": "New Users Daily Count",
        "Acceptance": "45.1%",
        "Difficulty": "Medium",
        "Frequency": "0",
        "Leetcode Question Link": " https://leetcode.com/problems/new-users-daily-count"
    },
    {
        "ID": "1127",
        "Title": "User Purchase Platform",
        "Acceptance": "48.9%",
        "Difficulty": "Hard",
        "Frequency": "0",
        "Leetcode Question Link": " https://leetcode.com/problems/user-purchase-platform"
    },
    {
        "ID": "1149",
        "Title": "Article Views II",
        "Acceptance": "48.2%",
        "Difficulty": "Medium",
        "Frequency": "0",
        "Leetcode Question Link": " https://leetcode.com/problems/article-views-ii"
    },
    {
        "ID": "1343",
        "Title": "Number of Sub-arrays of Size K and Average Greater than or Equal to Threshold",
        "Acceptance": "64.2%",
        "Difficulty": "Medium",
        "Frequency": "0",
        "Leetcode Question Link": " https://leetcode.com/problems/number-of-sub-arrays-of-size-k-and-average-greater-than-or-equal-to-threshold"
    }
]